pyui_automation/__init__.py
pyui_automation/accessibility.py
pyui_automation/application.py
pyui_automation/core.py
pyui_automation/di.py
pyui_automation/elements.py
pyui_automation/exceptions.py
pyui_automation/input.py
pyui_automation/logging.py
pyui_automation/ocr.py
pyui_automation/optimization.py
pyui_automation/performance.py
pyui_automation/visual.py
pyui_automation/wait.py
pyui_automation/backends/__init__.py
pyui_automation/backends/base.py
pyui_automation/backends/linux.py
pyui_automation/backends/macos.py
pyui_automation/backends/windows.py
pyui_automation/core/__init__.py
pyui_automation/core/config.py
pyui_automation/core/factory.py
pyui_automation/core/session.py
pyui_automation/core/utils.py
pyui_automation/elements/__init__.py
pyui_automation/elements/base.py
pyui_automation/elements/button.py
pyui_automation/elements/input.py
pyui_automation/elements/window.py
pyui_automation/utils/__init__.py
pyui_automation/utils/file.py
pyui_automation/utils/image.py
pyui_automation/utils/validation.py
pyui_automation-0.1.0.dist-info/METADATA
pyui_automation-0.1.0.dist-info/WHEEL
pyui_automation-0.1.0.dist-info/entry_points.txt
pyui_automation-0.1.0.dist-info/top_level.txt
pyui_automation-0.1.0.dist-info/RECORD
