Metadata-Version: 2.1
Name: pyui_automation
Version: 0.1.0
Summary: A powerful, cross-platform Python library for desktop UI testing and automation
Home-page: https://github.com/DaymaNKinG990/pyui_automation
Author: Ravil Shakerov
Author-email: your.email@example.com
Project-URL: Bug Tracker, https://github.com/DaymaNKinG990/pyui_automation/issues
Project-URL: Documentation, https://github.com/DaymaNKinG990/pyui_automation#readme
Project-URL: Source Code, https://github.com/DaymaNKinG990/pyui_automation
Keywords: ui automation,testing,gui testing,automation,accessibility testing,visual testing,performance testing,ocr,cross-platform
Classifier: Development Status :: 4 - Beta
Classifier: Intended Audience :: Developers
Classifier: Topic :: Software Development :: Testing
Classifier: Topic :: Software Development :: Quality Assurance
Classifier: Topic :: Software Development :: Libraries :: Python Modules
Classifier: License :: OSI Approved :: MIT License
Classifier: Programming Language :: Python :: 3
Classifier: Programming Language :: Python :: 3.8
Classifier: Programming Language :: Python :: 3.9
Classifier: Programming Language :: Python :: 3.10
Classifier: Programming Language :: Python :: 3.11
Classifier: Programming Language :: Python :: 3.12
Classifier: Operating System :: Microsoft :: Windows
Classifier: Operating System :: POSIX :: Linux
Classifier: Operating System :: MacOS :: MacOS X
Requires-Python: >=3.8
Requires-Dist: numpy>=1.24.0
Requires-Dist: opencv-python>=4.7.0
Requires-Dist: Pillow>=9.5.0
Requires-Dist: paddlepaddle>=2.5.1
Requires-Dist: paddleocr>=2.7.0
Requires-Dist: psutil>=5.9.0
Requires-Dist: matplotlib>=3.7.1
Requires-Dist: colour>=0.1.5
Requires-Dist: torch>=1.7.0
Requires-Dist: torchvision>=0.8.0
Requires-Dist: comtypes>=1.2.0
Requires-Dist: pywin32>=305
